go_mechanic/__init__.py
go_mechanic/manage.py
go_mechanic/autocare/__init__.py
go_mechanic/autocare/admin.py
go_mechanic/autocare/apps.py
go_mechanic/autocare/dynamodb.py
go_mechanic/autocare/models.py
go_mechanic/autocare/tests.py
go_mechanic/autocare/urls.py
go_mechanic/autocare/views.py
go_mechanic/backend/__init__.py
go_mechanic/backend/asgi.py
go_mechanic/backend/settings.py
go_mechanic/backend/urls.py
go_mechanic/backend/wsgi.py
go_mechanic_autocare_library-0.1.0.dist-info/METADATA
go_mechanic_autocare_library-0.1.0.dist-info/WHEEL
go_mechanic_autocare_library-0.1.0.dist-info/top_level.txt
go_mechanic_autocare_library-0.1.0.dist-info/RECORD
