Metadata-Version: 2.4
Name: go-mechanic-autocare-library
Version: 0.1.0
Summary: A Python library for auto care tracking using DynamoDB
Author: Mohan Morla
Author-email: morlamohansai@gmail.com
Classifier: Programming Language :: Python :: 3
Classifier: License :: OSI Approved :: MIT License
Classifier: Operating System :: OS Independent
Requires-Python: >=3.6
Requires-Dist: boto3
Dynamic: author
Dynamic: author-email
Dynamic: classifier
Dynamic: description-content-type
Dynamic: requires-dist
Dynamic: requires-python
Dynamic: summary
